interpies/__init__.py
interpies/colors.py
interpies/graphics.py
interpies/grid.py
interpies/segy_io.py
interpies/spatial.py
interpies/transforms.py
interpies-0.3.1.dist-info/DESCRIPTION.rst
interpies-0.3.1.dist-info/METADATA
interpies-0.3.1.dist-info/RECORD
interpies-0.3.1.dist-info/WHEEL
interpies-0.3.1.dist-info/metadata.json
interpies-0.3.1.dist-info/top_level.txt
