Metadata-Version: 2.0
Name: interpies
Version: 0.3.1
Summary: A collection of functions for reading, displaying, transforming and analyzing geophysical data.
Home-page: https://github.com/jobar8/interpies
Author: Joseph Barraud
Author-email: joseph.barraud@geophysicslabs.com
License: BSD
Keywords: geophysics raster gdal gravimetry magnetometry seismic
Platform: UNKNOWN
Classifier: Development Status :: 4 - Beta
Classifier: Intended Audience :: Science/Research
Classifier: Natural Language :: English
Classifier: License :: OSI Approved :: BSD License
Classifier: Operating System :: OS Independent
Classifier: Programming Language :: Python
Classifier: Programming Language :: Python :: 3.3
Classifier: Programming Language :: Python :: 3.4
Classifier: Programming Language :: Python :: 3.5
Classifier: Programming Language :: Python :: 3.6
Classifier: Topic :: Scientific/Engineering
Requires-Dist: matplotlib
Requires-Dist: numpy
Requires-Dist: rasterio (>=1.0a9)
Requires-Dist: scikit-image
Requires-Dist: scikit-learn
Requires-Dist: scipy
